islets/CrossfilterApp.py
islets/EventDistillery.py
islets/LineScan.py
islets/PicklePicker.py
islets/Recording.py
islets/Regions.py
islets/Regions3D.py
islets/__init__.py
islets/_manuscript_functions.py
islets/_purgatory.py
islets/examine.py
islets/examine_events.py
islets/fitting.py
islets/general_functions.py
islets/linescanner.py
islets/movie3D_functions.py
islets/movies.py
islets/numeric.py
islets/other.py
islets/plotly_hexbin.py
islets/protocol.py
islets/roiwriter.py
islets/serialization/Hdf5Serializer.py
islets/serialization/IDataSerializer.py
islets/serialization/JsonSerializer.py
islets/serialization/__init__.py
islets/serialization/simple.py
islets/utils.py
islets-0.7.5.dist-info/WHEEL
islets-0.7.5.dist-info/METADATA
islets-0.7.5.dist-info/RECORD
