Metadata-Version: 2.1
Name: islets
Version: 0.7.5
Summary: 
Home-page: https://github.com/Hannnsen/Physio_Ca_framework
Author: Srdjan Sarikas
Author-email: srdjan.sarikas@meduniwien.ac.at
Requires-Python: >=3.8,<3.11
Classifier: Intended Audience :: Science/Research
Classifier: Programming Language :: Python :: 3
Classifier: Programming Language :: Python :: 3.10
Classifier: Programming Language :: Python :: 3.8
Classifier: Programming Language :: Python :: 3.9
Classifier: Topic :: Scientific/Engineering :: Bio-Informatics
Classifier: Topic :: Scientific/Engineering :: Image Processing
Requires-Dist: bidict (>=0.22,<0.23)
Requires-Dist: dash (>=2.6.1,<3.0.0)
Requires-Dist: ffmpeg-python (>=0.2,<0.3)
Requires-Dist: jupyter-dash (>=0.4,<0.5)
Requires-Dist: jupyter-plotly-dash (>=0.4,<0.5)
Requires-Dist: llvmlite (==0.38.0)
Requires-Dist: matplotlib (>=3.5,<4.0)
Requires-Dist: mgzip (>=0.2,<0.3)
Requires-Dist: nd2reader (>=3.3,<4.0)
Requires-Dist: numba (>=0.55)
Requires-Dist: opencv-python (>=4.6,<5.0)
Requires-Dist: openpyxl (>=3.0.10,<4.0.0)
Requires-Dist: orjson (>=3.7,<4.0)
Requires-Dist: pandas (>=1.3.5,<1.4.0)
Requires-Dist: plotly (>=5.9,<6.0)
Requires-Dist: python-bioformats (>=4,<5)
Requires-Dist: python-javabridge (>=4,<5)
Requires-Dist: scikit-image (>=0.19,<0.20)
Requires-Dist: scikit-learn (>=1.1,<2.0)
Requires-Dist: scipy (>=1.9,<2.0)
Requires-Dist: statsmodels (>=0.13,<0.14)
Requires-Dist: tqdm (>=4.64,<5.0)
Requires-Dist: xlrd (>=2.0,<3.0)
Project-URL: Repository, https://github.com/Hannnsen/Physio_Ca_framework
